catt/__init__.py
catt/api.py
catt/cli.py
catt/controllers.py
catt/discovery.py
catt/error.py
catt/http_server.py
catt/stream_info.py
catt/subs_info.py
catt/util.py
catt-0.13.1.dist-info/AUTHORS.rst
catt-0.13.1.dist-info/LICENSE
catt-0.13.1.dist-info/METADATA
catt-0.13.1.dist-info/WHEEL
catt-0.13.1.dist-info/entry_points.txt
catt-0.13.1.dist-info/RECORD
