Metadata-Version: 2.3
Name: catt
Version: 0.13.1
Summary: Cast All The Things allows you to send videos from many, many online sources to your Chromecast.
License: BSD
Keywords: chromecast,cast,catt,cast_all_the_things
Author: Stavros Korokithakis
Author-email: hi@stavros.io
Requires-Python: >=3.11
Classifier: Development Status :: 5 - Production/Stable
Classifier: Intended Audience :: End Users/Desktop
Classifier: License :: OSI Approved :: BSD License
Classifier: License :: Other/Proprietary License
Classifier: Natural Language :: English
Classifier: Programming Language :: Python :: 3
Classifier: Programming Language :: Python :: 3.11
Classifier: Programming Language :: Python :: 3.12
Classifier: Programming Language :: Python :: 3.13
Requires-Dist: click (>=7.1.2)
Requires-Dist: ifaddr (>=0.1.7)
Requires-Dist: pychromecast (>=14.0.1,<15)
Requires-Dist: requests (>=2.23.0)
Requires-Dist: yt-dlp (>=2023.3.4)
Project-URL: Homepage, https://github.com/skorokithakis/catt
